{
  "alpha": {
    "start": 1,
    "end": 0
  },
  "scale": {
    "start": 0.3,
    "end": 1.5,
    "minimumScaleMultiplier": 0.1
  },
  "color": {
    "start": "#ffffff",
    "end": "#ffffff"
  },
  "speed": {
    "start": 800,
    "end": 400,
    "minimumSpeedMultiplier": 1
  },
  "acceleration": {
    "x": 0,
    "y": 1000
  },
  "maxSpeed": 0,
  "startRotation": {
    "min": 180,
    "max": 270
  },
  "noRotation": false,
  "rotationSpeed": {
    "min": 100,
    "max": 1000
  },
  "lifetime": {
    "min": 2.5,
    "max": 3.5
  },
  "blendMode": "normal",
  "frequency": 0.02,
  "emitterLifetime": 1.5,
  "maxParticles": 500,
  "pos": {
    "x": 0,
    "y": 0
  },
  "addAtBack": false,
  "spawnType": "point"
}